hmmlkit/__init__.py
hmmlkit-0.0.1a0.dist-info/LICENSE
hmmlkit-0.0.1a0.dist-info/METADATA
hmmlkit-0.0.1a0.dist-info/WHEEL
hmmlkit-0.0.1a0.dist-info/top_level.txt
hmmlkit-0.0.1a0.dist-info/RECORD
